hfs/__init__.py
hfs/__main__.py
hfs/bottle.py
hfs/constants.py
hfs/core.py
hfs/show_my_ip.py
hfs/html/curl-filelist.html
hfs/html/curl-listdir.html
hfs/html/filelist.html
hfs/html/listdir.html
hfs/static/jquery.min.js
hfs/static/main.css
hfs/static/main.js
hfs/static/qrcode.js
hfs-0.6.0.data/scripts/hfs
hfs-0.6.0.dist-info/DESCRIPTION.rst
hfs-0.6.0.dist-info/METADATA
hfs-0.6.0.dist-info/RECORD
hfs-0.6.0.dist-info/WHEEL
hfs-0.6.0.dist-info/metadata.json
hfs-0.6.0.dist-info/top_level.txt
