Metadata-Version: 2.0
Name: hfs
Version: 0.6.0
Summary: Tiny HTTP File Server
Home-page: https://github.com/pi314/hfs
Author: Cychih
Author-email: michael66230@gmail.com
License: WTFPL
Platform: UNKNOWN
Classifier: Development Status :: 1 - Planning
Classifier: Environment :: Console
Classifier: Intended Audience :: End Users/Desktop
Classifier: Natural Language :: Chinese (Traditional)
Classifier: Natural Language :: English
Classifier: Operating System :: MacOS :: MacOS X
Classifier: Programming Language :: Python :: 3 :: Only
Classifier: Topic :: Utilities
